[{"name":"FOlder ?!?!?!?!?","files":[{"name":"What","creationdate":1659548389747,"lastedited":1659810425861,"starred":false,"locked":false,"blocks":[{"creationdate":1659580541557,"type":"heading","text":"My Heading"},{"creationdate":1659580545568,"type":"text","text":"text block goes here"},{"creationdate":1659585789084,"type":"divider"},{"creationdate":1659723709710,"type":"heading","text":"Heading goes here"},{"creationdate":1659585790050,"type":"text","text":"this is my text block <div class=\"inline block inline_code\">code block is here</div>&nbsp;"},{"creationdate":1659810422002,"type":"text","text":"hello"}]}]},{"name":"Folder","files":[{"name":"File","creationdate":1659723641634,"lastedited":1659723641634,"starred":false,"locked":false,"blocks":[]}]},{"name":"New Folder","files":[{"name":"New File","creationdate":1659548390532,"lastedited":1659548390532,"starred":false,"locked":false,"blocks":[]}]}]